build/lib/build/lib/build/lib/build/lib/rtisdev/GenerateWiki.py
build/lib/build/lib/build/lib/build/lib/rtisdev/RTISDev.py
build/lib/build/lib/build/lib/build/lib/rtisdev/RTISGenerateSettings.py
build/lib/build/lib/build/lib/build/lib/rtisdev/__init__.py
build/lib/build/lib/build/lib/build/lib/rtisdev/simulate.bin
build/lib/build/lib/build/lib/build/lib/rtisdev/config/microphoneLayouts/eRTIS_v2/mic_coordinates.mat
build/lib/build/lib/build/lib/build/lib/rtisdev/config/microphoneLayouts/eRTIS_v2REC/mic_coordinates.mat
build/lib/build/lib/build/lib/build/lib/rtisdev/config/microphoneLayouts/eRTIS_v3D1/mic_coordinates.mat
build/lib/build/lib/build/lib/build/lib/rtisdev/config/microphoneLayouts/eRTIS_v3D1REC/mic_coordinates.mat
build/lib/build/lib/build/lib/build/lib/rtisdev/config/microphoneLayouts/uRTIS_v1/mic_coordinates.mat
build/lib/build/lib/build/lib/build/lib/rtisdev/config/microphoneLayouts/xRTIS_v1/mic_coordinates.mat
build/lib/build/lib/build/lib/build/lib/rtisdev/config/premadeSettings/processing/2D_5m_181.json
build/lib/build/lib/build/lib/build/lib/rtisdev/config/premadeSettings/processing/2D_5m_91.json
build/lib/build/lib/build/lib/build/lib/rtisdev/config/premadeSettings/processing/3D_10m_3000.json
build/lib/build/lib/build/lib/build/lib/rtisdev/config/premadeSettings/processing/3D_5m_1000.json
build/lib/build/lib/build/lib/build/lib/rtisdev/config/premadeSettings/processing/3D_5m_3000.json
build/lib/build/lib/build/lib/build/lib/rtisdev/config/premadeSettings/processing/3D_5m_4000.json
build/lib/build/lib/build/lib/build/lib/rtisdev/config/premadeSettings/processing/3D_5m_500.json
build/lib/build/lib/build/lib/build/lib/rtisdev/config/premadeSettings/processing/custom_example_2D_5m_91.json
build/lib/build/lib/build/lib/build/lib/rtisdev/config/premadeSettings/processing/delaymatrix.csv
build/lib/build/lib/build/lib/build/lib/rtisdev/config/premadeSettings/processing/directions.csv
rtisdev-2.15.1.dist-info/LICENSE
rtisdev-2.15.1.dist-info/METADATA
rtisdev-2.15.1.dist-info/WHEEL
rtisdev-2.15.1.dist-info/top_level.txt
rtisdev-2.15.1.dist-info/RECORD
