Metadata-Version: 2.1
Name: rtisdev
Version: 2.15.1
Summary: Python module to make it easy to code with RTIS devices
Author-email: Wouter Jansen <wouter.jansen@uantwerpen.be>, Arne Aerts <arne.aerts@uantwerpen.be>, Dennis Laurijssen <dennis.laurijssen@uantwerpen.be>, Jan Steckel <jan.steckel@uantwerpen.be>
Maintainer-email: Wouter Jansen <wouter.jansen@uantwerpen.be>
License: Attribution-NonCommercial-ShareAlike 4.0 International
Project-URL: Repository, https://cosysgit.uantwerpen.be/rtis-software/rtisdev
Project-URL: Documentation, https://cosysgit.uantwerpen.be/rtis-software/rtisdev/-/wikis/home
Keywords: rtisdev,rtis,sonar
Classifier: Development Status :: 6 - Mature
Classifier: Programming Language :: Python
Classifier: Programming Language :: Python :: 3
Classifier: Programming Language :: Python :: 3.6
Classifier: Programming Language :: Python :: 3.7
Classifier: Programming Language :: Python :: 3.8
Classifier: Programming Language :: Python :: 3.9
Classifier: Programming Language :: Python :: 3.10
Classifier: Programming Language :: Python :: 3.11
Classifier: Operating System :: Microsoft :: Windows
Classifier: Operating System :: Unix
Classifier: Topic :: Scientific/Engineering
Classifier: Topic :: Software Development
Requires-Python: >=3.6
License-File: LICENSE
Requires-Dist: scipy
Requires-Dist: numpy
Requires-Dist: multiprocessing-logging
Requires-Dist: uuid
